aos_sw_api/__init__.py
aos_sw_api/_client.py
aos_sw_api/_exceptions.py
aos_sw_api/_ip_address.py
aos_sw_api/_validate.py
aos_sw_api/auth/__init__.py
aos_sw_api/auth/_auth.py
aos_sw_api/enums/__init__.py
aos_sw_api/enums/device_operation_mode.py
aos_sw_api/enums/ip_address_version.py
aos_sw_api/enums/lacp_status.py
aos_sw_api/enums/mac_address_version.py
aos_sw_api/enums/port_config_mode.py
aos_sw_api/enums/port_trunk_type.py
aos_sw_api/enums/time_server_protocol.py
aos_sw_api/exceptions/__init__.py
aos_sw_api/exceptions/_exceptions.py
aos_sw_api/globel_models/__init__.py
aos_sw_api/globel_models/ip_address.py
aos_sw_api/globel_models/mac_address.py
aos_sw_api/globel_models/network_host.py
aos_sw_api/port/__init__.py
aos_sw_api/port/_model.py
aos_sw_api/port/_port.py
aos_sw_api/system/__init__.py
aos_sw_api/system/_model.py
aos_sw_api/system/_system.py
aos_sw_api/validate/__init__.py
aos_sw_api/validate/_validate.py
aos_sw_api-0.1.1.dist-info/LICENSE
aos_sw_api-0.1.1.dist-info/WHEEL
aos_sw_api-0.1.1.dist-info/METADATA
aos_sw_api-0.1.1.dist-info/RECORD
